README.md
setup.py
test/__init__.py
test/__main__.py
test/drivers_test.py
test/element_actions_test.py
test/extended_find_test.py
test/wait_test.py
webautomators/__init__.py
webautomators/actions.py
webautomators/exceptions.py
webautomators/expected_conditions.py
webautomators/extend_wait.py
webautomators/extended_driver.py
webautomators/extended_find.py
webautomators/extended_options.py
webautomators/extended_webelement.py
webautomators.egg-info/PKG-INFO
webautomators.egg-info/SOURCES.txt
webautomators.egg-info/dependency_links.txt
webautomators.egg-info/requires.txt
webautomators.egg-info/top_level.txt
webautomators.egg-info/zip-safe