Metadata-Version: 1.0
Name: webautomators
Version: 0.7
Summary: Application Interaction Library with Web
Home-page: UNKNOWN
Author: Raphael Peleje
Author-email: rmoreirap@indracompany.com
License: MIT License (MIT)
Platform: UNKNOWN
